scrapy_prometheus_plugin/__init__.py
scrapy_prometheus_plugin-0.0.4.dist-info/METADATA
scrapy_prometheus_plugin-0.0.4.dist-info/WHEEL
scrapy_prometheus_plugin-0.0.4.dist-info/RECORD
